thalosforge/__init__.py
thalosforge-1.0.1.dist-info/METADATA
thalosforge-1.0.1.dist-info/WHEEL
thalosforge-1.0.1.dist-info/entry_points.txt
thalosforge-1.0.1.dist-info/top_level.txt
thalosforge-1.0.1.dist-info/RECORD
