Metadata-Version: 2.4
Name: thalosforge
Version: 1.0.1
Summary: Enterprise optimization API client - CPLEX/Gurobi alternative
Author-email: "ThalosForge Inc." <support@thalosforge.com>
Maintainer-email: "ThalosForge Inc." <support@thalosforge.com>
License: Proprietary
Project-URL: Homepage, https://www.thalosforge.com
Project-URL: Documentation, https://www.thalosforge.com/documentation.html
Project-URL: Pricing, https://www.thalosforge.com/pricing.html
Keywords: optimization,mathematical-programming,constraint-programming,operations-research,cplex,gurobi,solver,api
Classifier: Development Status :: 5 - Production/Stable
Classifier: Intended Audience :: Developers
Classifier: Intended Audience :: Science/Research
Classifier: License :: Other/Proprietary License
Classifier: Operating System :: OS Independent
Classifier: Programming Language :: Python :: 3
Classifier: Programming Language :: Python :: 3.8
Classifier: Programming Language :: Python :: 3.9
Classifier: Programming Language :: Python :: 3.10
Classifier: Programming Language :: Python :: 3.11
Classifier: Programming Language :: Python :: 3.12
Classifier: Topic :: Scientific/Engineering :: Mathematics
Classifier: Topic :: Scientific/Engineering :: Artificial Intelligence
Requires-Python: >=3.8
Provides-Extra: cloud
Requires-Dist: requests>=2.25.0; extra == "cloud"
Provides-Extra: httpx
Requires-Dist: httpx>=0.24.0; extra == "httpx"
Provides-Extra: all
Requires-Dist: requests>=2.25.0; extra == "all"
Requires-Dist: httpx>=0.24.0; extra == "all"
Provides-Extra: dev
Requires-Dist: pytest>=7.0; extra == "dev"
Requires-Dist: black>=23.0; extra == "dev"
Requires-Dist: mypy>=1.0; extra == "dev"
